django_multiinfo/__init__.py
django_multiinfo/admin.py
django_multiinfo/app_settings.py
django_multiinfo/apps.py
django_multiinfo/factories.py
django_multiinfo/models.py
django_multiinfo/worker.py
django_multiinfo/management/__init__.py
django_multiinfo/management/commands/__init__.py
django_multiinfo/management/commands/delete_sent_queued_messages.py
django_multiinfo/management/commands/send_queued_messages.py
django_multiinfo/migrations/0001_initial.py
django_multiinfo/migrations/0002_auto_20180405_1814.py
django_multiinfo/migrations/0003_auto_20180427_1508.py
django_multiinfo/migrations/0004_auto_20180427_1548.py
django_multiinfo/migrations/0005_smsmessageinfo_dest.py
django_multiinfo/migrations/0006_auto_20180504_1015.py
django_multiinfo/migrations/0007_auto_20180808_1156.py
django_multiinfo/migrations/__init__.py
django_multiinfo-0.1.16.dist-info/METADATA
django_multiinfo-0.1.16.dist-info/RECORD
django_multiinfo-0.1.16.dist-info/WHEEL
django_multiinfo-0.1.16.dist-info/entry_points.txt
django_multiinfo-0.1.16.dist-info/top_level.txt
