Metadata-Version: 2.1
Name: django-multiinfo
Version: 0.1.16
Summary: Message queue for sending SMS messages through Polkomtel's MultiInfo service
Home-page: https://github.com/wooyek/django-multiinfo
Author: Janusz Skonieczny
Author-email: js+pypi@bravelabs.pl
License: UNKNOWN
Keywords: django-multiinfo
Platform: UNKNOWN
Classifier: Development Status :: 2 - Pre-Alpha
Classifier: Framework :: Django :: 1.10
Classifier: Intended Audience :: Developers
Classifier: Natural Language :: English
Classifier: Programming Language :: Python :: 2
Classifier: Programming Language :: Python :: 2.7
Classifier: Programming Language :: Python :: 3
Classifier: Programming Language :: Python :: 3.4
Classifier: Programming Language :: Python :: 3.5
Classifier: Programming Language :: Python :: 3.6
Classifier: Programming Language :: Python :: 3.7
Requires-Python: >=2.7
Provides-Extra: factories
Requires-Dist: click
Requires-Dist: django-environ
Requires-Dist: django-import-export
Requires-Dist: django-powerbank
Requires-Dist: dynaconf (==0.5.4)
Requires-Dist: multiinfo
Requires-Dist: requests
Requires-Dist: pathlib; python_version < "3.3"
Requires-Dist: enum34; python_version < "3.4"
Requires-Dist: django (>=2.0); python_version >= "3.5"
Provides-Extra: factories
Requires-Dist: factory-boy; extra == 'factories'
